{"version":"1","ruleDefinitions":[{"name":"Exabeam: Flatline rule to monitor Fortinet","description":"Alerts if less than 10 events from vendor in 4 hours.","useCase":"","mitre":[],"sequencesExecution":"CREATION_ORDER","severity":"none","sequencesConfig":{"sequences":[{"name":"","query":"vendor: \"Fortinet\"","condition":{"groupByOption":false,"groupBy":[],"functionType":"count","subject":"field","field":"activity_type","operator":"less_than","value":"10","time":4,"unit":"h","triggerOnAnyMatch":false},"id":"045fd65d-3fa6-4d4d-b20c-6f46f15141e7"}],"commonProperties":null,"outcomes":null}}]}